kattispdf/__init__.py
kattispdf/cli.py
kattispdf/kattispdf.py
kattispdf-1.0.7.dist-info/METADATA
kattispdf-1.0.7.dist-info/WHEEL
kattispdf-1.0.7.dist-info/entry_points.txt
kattispdf-1.0.7.dist-info/licenses/LICENSE
kattispdf-1.0.7.dist-info/RECORD
