Metadata-Version: 2.3
Name: kattispdf
Version: 1.0.7
Summary: It enables you to download pdf with problems from https://open.kattis.com
Project-URL: Homepage, https://github.com/NotTete/kattispdf
Author-email: Jorge Hdez <jorgehdezplp@proton.me>
License-File: LICENSE
Classifier: License :: OSI Approved :: MIT License
Classifier: Programming Language :: Python :: 3
Requires-Python: >=3.8
Requires-Dist: bs4
Requires-Dist: pylatex
Requires-Dist: requests
